{
  "project_info": {
    "project_number": "310317103295",
    "firebase_url": "https://fir-inventory-app-1e4ea.firebaseio.com",
    "project_id": "fir-inventory-app-1e4ea",
    "storage_bucket": "fir-inventory-app-1e4ea.appspot.com"
  },
  "client": [
    {
      "client_info": {
        "mobilesdk_app_id": "1:310317103295:android:1167253c5c88a3e2",
        "android_client_info": {
          "package_name": "com.myapplicationdev.android.demodialog.firebaseinventoryapp"
        }
      },
      "oauth_client": [
        {
          "client_id": "310317103295-evqipctfqnvepan8sogqfpcf8pgeohs5.apps.googleusercontent.com",
          "client_type": 3
        }
      ],
      "api_key": [
        {
          "current_key": "AIzaSyB_Mr143Bxf8QjSvKEHIKZd9MIzAuB86es"
        }
      ],
      "services": {
        "analytics_service": {
          "status": 1
        },
        "appinvite_service": {
          "status": 1,
          "other_platform_oauth_client": []
        },
        "ads_service": {
          "status": 2
        }
      }
    }
  ],
  "configuration_version": "1"
}